<xml>
<selection>
<title>Each student should select a unique large airport outside the US</title>
<filename>airports.csv</filename>
<destinations>
<id>KDEN</id><!--Include Denver in the tour-->
<!-- 
Add the id of your selected airport and a comment with your eName below this comment.  
I've provided an example with my selection above the comment.  
Must be a large airport outside of the US.  This information is provided in the airports.csv file.
NO DUPLICATES!
-->
<id>NZCH</id><!--davematt-->
<id>EHAM</id><!--bobfromholland-->
<id>EDDB</id><!--bmhogan-->
<id>VDPP</id><!--mepsheeh-->
<id>BIKF</id><!--nfredrik-->
<id>AYPY</id><!--ashellum-->
<id>ZYHB</id><!--athai-->
<id>ZYTX</id><!--wbrown--> 
<id>BKPR</id><!--cokin-->
<id>CYEG</id><!--maddendb-->
<id>LFOA</id><!--paultrap-->
<id>00PS</id><!--devbot-->
<id>EGLL</id><!--mejarrett-->
</destinations>
</selection>
</xml>